<?xml version="1.0" encoding="UTF-8"?><record_update table="sc_cat_item_category">
    <sc_cat_item_category action="INSERT_OR_UPDATE">
        <sc_cat_item display_value="Meu INSS">7aee7e9ddba9b304fd0a30cc299619fd</sc_cat_item>
        <sc_category display_value="Serviços ao Cidadão">f7230b15dbe9b304fd0a30cc2996191b</sc_category>
        <sys_class_name>sc_cat_item_category</sys_class_name>
        <sys_created_by>admin</sys_created_by>
        <sys_created_on>2019-05-20 15:50:22</sys_created_on>
        <sys_id>0a044b55dbe9b304fd0a30cc2996192c</sys_id>
        <sys_mod_count>0</sys_mod_count>
        <sys_name>Serviços ao Cidadão.Meu INSS</sys_name>
        <sys_package display_value="CIOGOV" source="x_snc_ciogov">23c50659db65b304fd0a30cc299619f2</sys_package>
        <sys_policy/>
        <sys_scope display_value="CIOGOV">23c50659db65b304fd0a30cc299619f2</sys_scope>
        <sys_update_name>sc_cat_item_category_0a044b55dbe9b304fd0a30cc2996192c</sys_update_name>
        <sys_updated_by>admin</sys_updated_by>
        <sys_updated_on>2019-05-20 15:50:22</sys_updated_on>
    </sc_cat_item_category>
</record_update>
